topsis_charu_102303113/__init__.py
topsis_charu_102303113/topsis.py
topsis_charu_102303113-1.0.1.dist-info/licenses/LICENSE
topsis_charu_102303113-1.0.1.dist-info/METADATA
topsis_charu_102303113-1.0.1.dist-info/WHEEL
topsis_charu_102303113-1.0.1.dist-info/top_level.txt
topsis_charu_102303113-1.0.1.dist-info/RECORD
