Metadata-Version: 2.4
Name: Topsis-Charu-102303113
Version: 1.0.1
Summary: TOPSIS implementation as a Python package
Author: Charu
Author-email: your_email@gmail.com
License-File: LICENSE
Requires-Dist: numpy
Requires-Dist: pandas
Dynamic: author
Dynamic: author-email
Dynamic: description
Dynamic: description-content-type
Dynamic: license-file
Dynamic: requires-dist
Dynamic: summary
